agroweekpy/__init__.py
agroweekpy/client.py
agroweekpy/core.py
agroweekpy/publisher.py
agroweekpy/subscriber.py
agroweekpy/msg/__init__.py
agroweekpy/msg/motor_command.py
agroweekpy/msg/odometry.py
agroweekpy/msg/yaw.py
agroweekpy-1.0.1.dist-info/METADATA
agroweekpy-1.0.1.dist-info/WHEEL
agroweekpy-1.0.1.dist-info/top_level.txt
agroweekpy-1.0.1.dist-info/RECORD
